apple_weatherkit/__init__.py
apple_weatherkit/client.py
apple_weatherkit-1.1.2.dist-info/LICENSE
apple_weatherkit-1.1.2.dist-info/METADATA
apple_weatherkit-1.1.2.dist-info/WHEEL
apple_weatherkit-1.1.2.dist-info/RECORD
