Metadata-Version: 2.1
Name: apple_weatherkit
Version: 1.1.2
Summary: Python client for Apple WeatherKit API
Home-page: https://github.com/tjhorner/python-weatherkit
Author: TJ Horner
Author-email: me@tjhorner.com
Requires-Python: >=3.11,<4.0
Classifier: Programming Language :: Python :: 3
Classifier: Programming Language :: Python :: 3.11
Requires-Dist: aiohttp (>=3.8.5,<4.0.0)
Requires-Dist: aiohttp-retry (>=2.8.3,<3.0.0)
Requires-Dist: pyjwt[crypto] (==2.*)
Project-URL: Repository, https://github.com/tjhorner/python-weatherkit
